mdal/__init__.py
mdal/conf.py
mdal/libmdalpython.cp310-win_amd64.pyd
mdal/transform.py
mdal_python-1.0.3.dist-info/LICENSE
mdal_python-1.0.3.dist-info/METADATA
mdal_python-1.0.3.dist-info/WHEEL
mdal_python-1.0.3.dist-info/top_level.txt
mdal_python-1.0.3.dist-info/RECORD
