Metadata-Version: 2.1
Name: mdal-python
Version: 1.0.3
Summary: Mesh data processing
Home-page: https://www.mdal.xyz
Author: Paul Harwood
Author-email: runette@gmail.com
Maintainer: Paul Harwood
Maintainer-email: runette@gmail.com
License: MIT
Keywords: mesh data spatial
Classifier: Development Status :: 4 - Beta
Classifier: Intended Audience :: Developers
Classifier: Intended Audience :: Science/Research
Classifier: License :: OSI Approved :: MIT License
Classifier: Operating System :: OS Independent
Classifier: Programming Language :: Python :: 3.9
Classifier: Programming Language :: Python :: 3.10
Classifier: Programming Language :: Python :: 3.11
Classifier: Programming Language :: Python :: 3.12
Classifier: Topic :: Scientific/Engineering :: GIS
License-File: LICENSE
Requires-Dist: numpy
Requires-Dist: meshio
